.gitignore
MANIFEST.in
README.rst
setup.cfg
setup.py
docs/HISTORY.txt
raptus/__init__.py
raptus.princexml.egg-info/PKG-INFO
raptus.princexml.egg-info/SOURCES.txt
raptus.princexml.egg-info/dependency_links.txt
raptus.princexml.egg-info/entry_points.txt
raptus.princexml.egg-info/namespace_packages.txt
raptus.princexml.egg-info/not-zip-safe
raptus.princexml.egg-info/requires.txt
raptus.princexml.egg-info/top_level.txt
raptus/princexml/__init__.py
raptus/princexml/configure.zcml
raptus/princexml/converter.py
raptus/princexml/interfaces.py