Metadata-Version: 1.1
Name: raptus.princexml
Version: 1.0a3
Summary: Provides a simple bridge to create PDFs from HTML views using PrinceXML
Home-page: https://github.com/Raptus/raptus.princexml
Author: Raptus AG
Author-email: dev@raptus.com
License: GPL
Platform: UNKNOWN
Classifier: Programming Language :: Python
Classifier: Topic :: Software Development :: Libraries :: Python Modules
